simpletree
