Metadata-Version: 1.0
Name: simpletree
Version: 0.1.1beta
Summary: Fastest and simplest tree implementation for Django framework.
